ipag_cred2/__init__.py
ipag_cred2/client.py
ipag_cred2/config.py
ipag_cred2/cred2.py
ipag_cred2/define.py
ipag_cred2/io.py
ipag_cred2/metadata_model.py
ipag_cred2/setup.py
ipag_cred2/sim.py
ipag_cred2/state.py
ipag_cred2-0.1.3.dist-info/METADATA
ipag_cred2-0.1.3.dist-info/WHEEL
ipag_cred2-0.1.3.dist-info/RECORD
